LICENSE
README.md
setup.cfg
setup.py
cpk.egg-info/PKG-INFO
cpk.egg-info/SOURCES.txt
cpk.egg-info/dependency_links.txt
cpk.egg-info/not-zip-safe
cpk.egg-info/requires.txt
cpk.egg-info/top_level.txt
include/cpk/__init__.py
include/cpk/config.py
include/cpk/constants.py
include/cpk/exceptions.py
include/cpk/machine.py
include/cpk/project.py
include/cpk/schemas.py
include/cpk/types.py
include/cpk/adapters/__init__.py
include/cpk/adapters/cli.py
include/cpk/adapters/fs.py
include/cpk/adapters/generic.py
include/cpk/adapters/git.py
include/cpk/adapters/null.py
include/cpk/adapters/project.py
include/cpk/bin/cpk
include/cpk/cli/__init__.py
include/cpk/cli/logger.py
include/cpk/cli/main.py
include/cpk/cli/commands/__init__.py
include/cpk/cli/commands/build.py
include/cpk/cli/commands/clean.py
include/cpk/cli/commands/create.py
include/cpk/cli/commands/decorate.py
include/cpk/cli/commands/info.py
include/cpk/cli/commands/pull.py
include/cpk/cli/commands/push.py
include/cpk/cli/commands/run.py
include/cpk/cli/commands/endpoint/__init__.py
include/cpk/cli/commands/endpoint/info.py
include/cpk/cli/commands/machine/__init__.py
include/cpk/cli/commands/machine/create.py
include/cpk/cli/commands/machine/info.py
include/cpk/cli/commands/machine/list.py
include/cpk/cli/commands/machine/remove.py
include/cpk/decorator/.dockerignore
include/cpk/decorator/Dockerfile
include/cpk/decorator/README.md
include/cpk/decorator/dependencies-apt.txt
include/cpk/decorator/dependencies-py3.txt
include/cpk/decorator/project.cpk
include/cpk/decorator/setup.sh
include/cpk/decorator/assets/entrypoint.sh
include/cpk/decorator/assets/environment.sh
include/cpk/decorator/assets/bin/cpk-apt-install
include/cpk/decorator/assets/bin/cpk-assert-argument-equal
include/cpk/decorator/assets/bin/cpk-assert-argument-not-empty
include/cpk/decorator/assets/bin/cpk-assert-argument-not-equal
include/cpk/decorator/assets/bin/cpk-install-launchers
include/cpk/decorator/assets/bin/cpk-install-packages-dependencies
include/cpk/decorator/assets/bin/cpk-pip3-install
include/cpk/decorator/assets/bin/cpk-set-container-healthy
